hf_model_s/__init__.py
hf_model_s/model_s.py
hf_model_s/model_s.py-
hf_model_s-0.1.0.dist-info/LICENSE
hf_model_s-0.1.0.dist-info/WHEEL
hf_model_s-0.1.0.dist-info/METADATA
hf_model_s-0.1.0.dist-info/RECORD
