Metadata-Version: 2.1
Name: hf-model-s
Version: 0.1.0
Summary: model-s served from hf spaces
Home-page: https://github.com/ffreemt/model-s
License: MIT
Author: ffreemt
Requires-Python: >=3.8.3,<4.0.0
Classifier: License :: OSI Approved :: MIT License
Classifier: Programming Language :: Python :: 3
Classifier: Programming Language :: Python :: 3.10
Classifier: Programming Language :: Python :: 3.9
Requires-Dist: alive-progress (>=2.4.1,<3.0.0)
Requires-Dist: huggingface-hub (>=0.5.1,<0.6.0)
Requires-Dist: joblib (>=1.1.0,<2.0.0)
Requires-Dist: logzero (>=1.7.0,<2.0.0)
Requires-Dist: sentence-transformers (>=2.2.0,<3.0.0)
Project-URL: Repository, https://github.com/ffreemt/model-s
